alpha101/__init__.py
alpha101/alphas.py
alpha101-0.1.0.dist-info/WHEEL
alpha101-0.1.0.dist-info/entry_points.txt
alpha101-0.1.0.dist-info/METADATA
alpha101-0.1.0.dist-info/RECORD
