Metadata-Version: 2.3
Name: alpha101
Version: 0.1.0
Summary: A Python implementation of the 101 Formulaic Alphas by WorldQuant.
Author: lvlh2
Author-email: lvlh2 <lvlh2@outlook.com>
Requires-Dist: pandas>=2.3.3
Requires-Python: >=3.13
Project-URL: repository, https://github.com/lvlh2/alpha101
